cg_plot_capture/__init__.py
cg_plot_capture/backend.py
cg_plot_capture-1.0.1.dist-info/METADATA
cg_plot_capture-1.0.1.dist-info/WHEEL
cg_plot_capture-1.0.1.dist-info/entry_points.txt
cg_plot_capture-1.0.1.dist-info/RECORD
