Metadata-Version: 2.4
Name: cg-plot-capture
Version: 1.0.1
Summary: Capture and send matplotlib plots via send_file
Author-email: CodeGrade <info@codegrade.com>
License-Expression: MIT
Requires-Python: ~=3.10
Requires-Dist: matplotlib<4.0.0,>=3.6.0
Provides-Extra: plotnine
Requires-Dist: plotnine>=0.12.0; extra == 'plotnine'
Provides-Extra: seaborn
Requires-Dist: seaborn>=0.12.0; extra == 'seaborn'
